xboc/__init__.py
xboc/model.py
xboc/prompts.py
xboc/types.py
xboc/utils.py
xboc-0.1.2.dist-info/LICENSE
xboc-0.1.2.dist-info/METADATA
xboc-0.1.2.dist-info/WHEEL
xboc-0.1.2.dist-info/RECORD
