Metadata-Version: 2.1
Name: xboc
Version: 0.1.2
Summary: Explainable Bag-Of-Concepts implementation with automatic concept labelling using a LLM pipeline.
Author: Kristiyan Sakalyan
Author-email: kristiyan.sakalyan@tum.de
Requires-Python: ==3.11.*
Classifier: Programming Language :: Python :: 3
Classifier: Programming Language :: Python :: 3.11
Requires-Dist: langchain (>=0.1.9,<0.2.0)
Requires-Dist: langchain-community (>=0.0.22,<0.0.23)
Requires-Dist: langchain-openai (>=0.0.7,<0.0.8)
Requires-Dist: numpy (==1.23.5)
Requires-Dist: openai (>=1.3.9,<2.0.0)
Requires-Dist: pandas (>=2.2.0,<3.0.0)
Requires-Dist: pickle4 (>=0.0.1,<0.0.2)
Requires-Dist: rich (>=13.7.0,<14.0.0)
Requires-Dist: scikit-learn (>=1.4.1.post1,<2.0.0)
Requires-Dist: scipy (>=1.12.0,<2.0.0)
Requires-Dist: soyclustering (>=0.2.0,<0.3.0)
Requires-Dist: sphinx-rtd-theme (>=2.0.0,<3.0.0)
